levelapp/__init__.py
levelapp/aspects/__init__.py
levelapp/aspects/loader.py
levelapp/aspects/logger.py
levelapp/aspects/monitor.py
levelapp/aspects/sanitizer.py
levelapp/clients/__init__.py
levelapp/clients/anthropic.py
levelapp/clients/gemini.py
levelapp/clients/groq.py
levelapp/clients/huggingface.py
levelapp/clients/ionos.py
levelapp/clients/mistral.py
levelapp/clients/openai.py
levelapp/comparator/__init__.py
levelapp/comparator/comparator.py
levelapp/comparator/extractor.py
levelapp/comparator/schemas.py
levelapp/comparator/scorer.py
levelapp/comparator/utils.py
levelapp/config/__init__.py
levelapp/config/endpoint.py
levelapp/config/prompts.py
levelapp/core/__init__.py
levelapp/core/base.py
levelapp/core/schemas.py
levelapp/core/session.py
levelapp/endpoint/__init__.py
levelapp/endpoint/client.py
levelapp/endpoint/client_test.py
levelapp/endpoint/manager.py
levelapp/endpoint/parsers.py
levelapp/endpoint/schemas.py
levelapp/endpoint/tester.py
levelapp/evaluator/__init__.py
levelapp/evaluator/evaluator.py
levelapp/metrics/__init__.py
levelapp/metrics/embedding.py
levelapp/metrics/exact.py
levelapp/metrics/fuzzy.py
levelapp/metrics/token.py
levelapp/metrics/embeddings/__init__.py
levelapp/metrics/embeddings/sentence_transformer.py
levelapp/metrics/embeddings/torch_based.py
levelapp/plugins/__init__.py
levelapp/repository/__init__.py
levelapp/repository/filesystem.py
levelapp/repository/firestore.py
levelapp/simulator/__init__.py
levelapp/simulator/schemas.py
levelapp/simulator/simulator.py
levelapp/simulator/utils.py
levelapp/visualization/__init__.py
levelapp/visualization/charts.py
levelapp/visualization/dashboard.py
levelapp/visualization/exporter.py
levelapp/visualization/templates/base.html
levelapp/visualization/templates/comparator_dashboard.html
levelapp/visualization/templates/simulator_dashboard.html
levelapp/workflow/__init__.py
levelapp/workflow/base.py
levelapp/workflow/config.py
levelapp/workflow/context.py
levelapp/workflow/factory.py
levelapp-0.1.15.dist-info/METADATA
levelapp-0.1.15.dist-info/WHEEL
levelapp-0.1.15.dist-info/licenses/LICENSE
levelapp-0.1.15.dist-info/RECORD
