Metadata-Version: 2.4
Name: levelapp
Version: 0.1.15
Summary: LevelApp is an evaluation framework for AI/LLM-based software application. [Powered by Norma]
Project-URL: Homepage, https://github.com/levelapp-org
Project-URL: Repository, https://github.com/levelapp-org/levelapp-framework
Project-URL: Documentation, https://levelapp.readthedocs.io
Project-URL: Issues, https://github.com/levelapp-org/levelapp-framework/issues
Author-email: Mohamed Sofiene KADRI <ms.kadri.dev@gmail.com>
License-File: LICENSE
Keywords: ai,evaluation,framework,llm,testing
Classifier: Development Status :: 3 - Alpha
Classifier: Intended Audience :: Developers
Classifier: License :: OSI Approved :: MIT License
Classifier: Programming Language :: Python :: 3
Classifier: Programming Language :: Python :: 3.12
Classifier: Topic :: Scientific/Engineering :: Artificial Intelligence
Classifier: Topic :: Software Development :: Testing
Requires-Python: >=3.12
Requires-Dist: backoff>=2.2.1
Requires-Dist: google-api-core>=2.25.1
Requires-Dist: google-auth>=2.40.3
Requires-Dist: google-cloud-firestore>=2.21.0
Requires-Dist: httpx>=0.28.1
Requires-Dist: humanize>=4.13.0
Requires-Dist: numpy>=2.3.2
Requires-Dist: pandas-stubs==2.3.0.250703
Requires-Dist: pandas>=2.3.1
Requires-Dist: pydantic>=2.11.7
Requires-Dist: python-dotenv>=1.1.1
Requires-Dist: pyyaml>=6.0.2
Requires-Dist: rapid>=0.0.3
Requires-Dist: rapidfuzz>=3.13.0
Requires-Dist: requests>=2.32.4
Requires-Dist: tenacity>=9.1.2
Provides-Extra: dev
Requires-Dist: google-api-core>=2.25.1; extra == 'dev'
Requires-Dist: google-auth>=2.40.3; extra == 'dev'
Requires-Dist: google-cloud-firestore>=2.21.0; extra == 'dev'
Requires-Dist: httpx>=0.28.1; extra == 'dev'
Requires-Dist: humanize>=4.13.0; extra == 'dev'
Requires-Dist: numpy>=2.3.2; extra == 'dev'
Requires-Dist: pandas-stubs==2.3.0.250703; extra == 'dev'
Requires-Dist: pandas>=2.3.1; extra == 'dev'
Requires-Dist: pydantic>=2.11.7; extra == 'dev'
Requires-Dist: python-dotenv>=1.1.1; extra == 'dev'
Requires-Dist: pyyaml>=6.0.2; extra == 'dev'
Requires-Dist: rapid>=0.0.3; extra == 'dev'
Requires-Dist: rapidfuzz>=3.13.0; extra == 'dev'
Requires-Dist: requests>=2.32.4; extra == 'dev'
Requires-Dist: tenacity>=9.1.2; extra == 'dev'
Provides-Extra: embeddings
Requires-Dist: bert-score>=0.3; extra == 'embeddings'
Requires-Dist: torch>=2.0; extra == 'embeddings'
Requires-Dist: transformers>=4.40; extra == 'embeddings'
